MANIFEST.in
README.md
setup.py
kextractors/kextractor-3.19/bconf.lex.c
kextractors/kextractor-3.19/bconf.tab.c
kextractors/kextractor-3.19/confdata.c
kextractors/kextractor-3.19/expr.c
kextractors/kextractor-3.19/expr.h
kextractors/kextractor-3.19/kextractor.c
kextractors/kextractor-3.19/kextractor_extension.c
kextractors/kextractor-3.19/list.h
kextractors/kextractor-3.19/lkc.h
kextractors/kextractor-3.19/lkc_proto.h
kextractors/kextractor-3.19/menu.c
kextractors/kextractor-3.19/symbol.c
kextractors/kextractor-3.19/util.c
kextractors/kextractor-3.19/zconf.hash.c
kextractors/kextractor-3.19/zconf.lex.c
kextractors/kextractor-3.19/zconf.tab.c
kextractors/kextractor-3.2/bconf.lex.c
kextractors/kextractor-3.2/bconf.tab.c
kextractors/kextractor-3.2/confdata.c
kextractors/kextractor-3.2/expr.c
kextractors/kextractor-3.2/expr.h
kextractors/kextractor-3.2/kextractor.c
kextractors/kextractor-3.2/kextractor_extension.c
kextractors/kextractor-3.2/lkc.h
kextractors/kextractor-3.2/lkc_proto.h
kextractors/kextractor-3.2/menu.c
kextractors/kextractor-3.2/symbol.c
kextractors/kextractor-3.2/util.c
kextractors/kextractor-3.2/zconf.hash.c
kextractors/kextractor-3.2/zconf.lex.c
kextractors/kextractor-3.2/zconf.tab.c
kextractors/kextractor-4.12.8/bconf.lex.c
kextractors/kextractor-4.12.8/bconf.tab.c
kextractors/kextractor-4.12.8/confdata.c
kextractors/kextractor-4.12.8/expr.c
kextractors/kextractor-4.12.8/expr.h
kextractors/kextractor-4.12.8/kextractor.c
kextractors/kextractor-4.12.8/kextractor_extension.c
kextractors/kextractor-4.12.8/list.h
kextractors/kextractor-4.12.8/lkc.h
kextractors/kextractor-4.12.8/lkc_proto.h
kextractors/kextractor-4.12.8/menu.c
kextractors/kextractor-4.12.8/symbol.c
kextractors/kextractor-4.12.8/util.c
kextractors/kextractor-4.12.8/zconf.hash.c
kextractors/kextractor-4.12.8/zconf.lex.c
kextractors/kextractor-4.12.8/zconf.tab.c
kextractors/kextractor-4.18/confdata.c
kextractors/kextractor-4.18/expr.c
kextractors/kextractor-4.18/expr.h
kmax.egg-info/PKG-INFO
kmax.egg-info/SOURCES.txt
kmax.egg-info/dependency_links.txt
kmax.egg-info/requires.txt
kmax.egg-info/top_level.txt
