Metadata-Version: 2.1
Name: kmax
Version: 4.7.3
Summary: Tools for working with symbolic  constraints from Kbuild Makefile.
Home-page: https://github.com/paulgazz/kmax
Author: Paul Gazzillo
Author-email: paul@pgazz.com
License: GPLv2+
Keywords: makefile kconfig kbuild configurations kmax kclause klocalizer
Classifier: Development Status :: 4 - Beta
Classifier: Topic :: Utilities
Classifier: License :: OSI Approved :: GNU General Public License v2 or later (GPLv2+)
